pyfftw/__init__.pxd
pyfftw/__init__.py
pyfftw/_version.py
pyfftw/config.py
pyfftw/cpu.pxd
pyfftw/pyfftw.cpython-314-aarch64-linux-gnu.so
pyfftw/pyfftw.pxd
pyfftw/pyfftw.pyx
pyfftw/utils.pxi
pyfftw/builders/__init__.py
pyfftw/builders/_utils.py
pyfftw/builders/builders.py
pyfftw/interfaces/__init__.py
pyfftw/interfaces/_utils.py
pyfftw/interfaces/cache.py
pyfftw/interfaces/dask_fft.py
pyfftw/interfaces/numpy_fft.py
pyfftw/interfaces/scipy_fft.py
pyfftw/interfaces/scipy_fftpack.py
pyfftw.libs/libfftw3-b7546720.so.3.5.5
pyfftw.libs/libfftw3_omp-813bb571.so.3.5.5
pyfftw.libs/libfftw3f-e06f4164.so.3.5.5
pyfftw.libs/libfftw3f_omp-52cb7832.so.3.5.5
pyfftw.libs/libfftw3l-b4722b94.so.3.5.5
pyfftw.libs/libfftw3l_omp-8746f69d.so.3.5.5
pyfftw.libs/libgomp-a49a47f9.so.1.0.0
pyfftw-0.15.1.dist-info/METADATA
pyfftw-0.15.1.dist-info/WHEEL
pyfftw-0.15.1.dist-info/top_level.txt
pyfftw-0.15.1.dist-info/RECORD
pyfftw-0.15.1.dist-info/licenses/LICENSE.txt
