Metadata-Version: 2.4
Name: pyFFTW
Version: 0.15.1
Summary: A pythonic wrapper around FFTW, the FFT library, presenting a unified interface for all the supported transforms.
Author-email: Henry Gomersall <heng@kedevelopments.co.uk>
License-Expression: BSD-3-Clause
Project-URL: Homepage, https://github.com/pyFFTW/pyFFTW
Classifier: Development Status :: 5 - Production/Stable
Classifier: Intended Audience :: Developers
Classifier: Intended Audience :: Science/Research
Classifier: Operating System :: OS Independent
Classifier: Programming Language :: Python
Classifier: Programming Language :: Python :: 3
Classifier: Programming Language :: Python :: 3.11
Classifier: Programming Language :: Python :: 3.12
Classifier: Programming Language :: Python :: 3.13
Classifier: Topic :: Multimedia :: Sound/Audio :: Analysis
Classifier: Topic :: Scientific/Engineering
Classifier: Topic :: Scientific/Engineering :: Image Processing
Classifier: Topic :: Scientific/Engineering :: Mathematics
Classifier: Topic :: Scientific/Engineering :: Physics
Requires-Python: >=3.11
License-File: LICENSE.txt
Requires-Dist: numpy>=1.20
Provides-Extra: dask
Requires-Dist: dask[array]>=1.0; extra == "dask"
Requires-Dist: numpy>=1.20; extra == "dask"
Provides-Extra: scipy
Requires-Dist: scipy>=1.8.0; extra == "scipy"
Dynamic: license-file
